civetqc/__init__.py
civetqc/data.py
civetqc/exceptions.py
civetqc/main.py
civetqc/model.py
civetqc/train.py
civetqc/utils.py
civetqc/resources/model.pkl
civetqc-0.1.6.dist-info/LICENSE
civetqc-0.1.6.dist-info/METADATA
civetqc-0.1.6.dist-info/WHEEL
civetqc-0.1.6.dist-info/entry_points.txt
civetqc-0.1.6.dist-info/top_level.txt
civetqc-0.1.6.dist-info/RECORD
