Metadata-Version: 2.1
Name: civetqc
Version: 0.1.6
Summary: CivetQC is a command-line tool for automated quality control of CIVET outputs
Author-email: Joshua Unrau <contact@joshuaunrau.com>
License: MIT
Project-URL: Homepage, https://github.com/joshunrau/civetqc
Project-URL: Bug Tracker, https://github.com/joshunrau/civetqc/issues
Keywords: CIVET,QC
Classifier: Development Status :: 4 - Beta
Classifier: Programming Language :: Python :: 3
Classifier: Programming Language :: Python :: 3.9
Classifier: Programming Language :: Python :: 3.10
Classifier: Programming Language :: Python :: 3.11
Classifier: License :: OSI Approved :: MIT License
Classifier: Operating System :: OS Independent
Requires-Python: >=3.9
License-File: LICENSE
Requires-Dist: scikit-learn (==1.1.1)
Requires-Dist: numpy (==1.23.2)
Requires-Dist: imbalanced-learn (==0.9.1)
Provides-Extra: development
Requires-Dist: black (>=22.6.0) ; extra == 'development'
Requires-Dist: build (>=0.9.0) ; extra == 'development'
Requires-Dist: matplotlib (>=3.5.3) ; extra == 'development'
Requires-Dist: mypy (>=0.971) ; extra == 'development'
Requires-Dist: pandas (>=1.4.3) ; extra == 'development'
Requires-Dist: scipy (>=1.9.0) ; extra == 'development'
Requires-Dist: twine (>=4.0.1) ; extra == 'development'
Requires-Dist: types-pkg-resources (>=0.1.3) ; extra == 'development'
Requires-Dist: types-setuptools (>=61.0) ; extra == 'development'
Requires-Dist: yellowbrick (>=1.5) ; extra == 'development'
